pypfilt/__init__.py
pypfilt/adaptive.py
pypfilt/build.py
pypfilt/cache.py
pypfilt/crps.py
pypfilt/event.py
pypfilt/io.py
pypfilt/model.py
pypfilt/obs.py
pypfilt/pfilter.py
pypfilt/plot.py
pypfilt/resample.py
pypfilt/sampler.py
pypfilt/scenario.py
pypfilt/state.py
pypfilt/stats.py
pypfilt/summary.py
pypfilt/time.py
pypfilt/examples/__init__.py
pypfilt/examples/gaussian_walk.toml
pypfilt/examples/lorenz.py
pypfilt/examples/predation-counts-x-datetime.ssv
pypfilt/examples/predation-counts-x.ssv
pypfilt/examples/predation-counts-y-datetime.ssv
pypfilt/examples/predation-counts-y.ssv
pypfilt/examples/predation-datetime.toml
pypfilt/examples/predation.py
pypfilt/examples/predation.toml
pypfilt/examples/simple.py
pypfilt/examples/sir.py
pypfilt/examples/sir.toml
pypfilt/examples/sirv.py
pypfilt/examples/sirv.toml
pypfilt-0.8.7.dist-info/METADATA
pypfilt-0.8.7.dist-info/WHEEL
pypfilt-0.8.7.dist-info/licenses/LICENSE
pypfilt-0.8.7.dist-info/RECORD
