Metadata-Version: 2.4
Name: pypfilt
Version: 0.8.7
Summary: Particle filters for Python
Project-URL: homepage, https://bitbucket.org/robmoss/particle-filter-for-python/
Project-URL: repository, https://bitbucket.org/robmoss/particle-filter-for-python/
Project-URL: documentation, https://pypfilt.readthedocs.io/en/latest/
Project-URL: changelog, https://pypfilt.readthedocs.io/en/latest/changelog.html
Author-email: Rob Moss <rgmoss@unimelb.edu.au>
Maintainer-email: Rob Moss <rgmoss@unimelb.edu.au>
License: Copyright (c) 2014-2025, Rob Moss
License-File: LICENSE
Classifier: Development Status :: 4 - Beta
Classifier: Intended Audience :: Science/Research
Classifier: License :: OSI Approved :: BSD License
Classifier: Operating System :: OS Independent
Classifier: Programming Language :: Python
Classifier: Programming Language :: Python :: 3
Classifier: Topic :: Scientific/Engineering :: Mathematics
Requires-Python: >=3.8
Requires-Dist: h5py~=3.0
Requires-Dist: lhs~=0.4
Requires-Dist: numpy>=1.19.5
Requires-Dist: packaging>=21.3
Requires-Dist: scipy~=1.10
Requires-Dist: tomli-w~=1.0
Requires-Dist: tomli~=2.0
Provides-Extra: all
Requires-Dist: matplotlib~=3.6; extra == 'all'
Requires-Dist: pandas~=2.0; extra == 'all'
Requires-Dist: polars~=1.0; extra == 'all'
Provides-Extra: pandas
Requires-Dist: pandas~=2.0; extra == 'pandas'
Provides-Extra: plot
Requires-Dist: matplotlib~=3.6; extra == 'plot'
Provides-Extra: polars
Requires-Dist: polars~=1.0; extra == 'polars'
Provides-Extra: tests
Requires-Dist: pytest-cov>=4.0; extra == 'tests'
Requires-Dist: pytest>=8.1.1; extra == 'tests'
